airflow_django/__init__.py
airflow_django/operators.py
airflow_django-0.7.0.dist-info/WHEEL
airflow_django-0.7.0.dist-info/METADATA
airflow_django-0.7.0.dist-info/RECORD
